odoo9_addon_project_closing-9.0.0.1.1.99.dev5-py2.7-nspkg.pth
odoo9_addon_project_closing-9.0.0.1.1.99.dev5.dist-info/METADATA
odoo9_addon_project_closing-9.0.0.1.1.99.dev5.dist-info/RECORD
odoo9_addon_project_closing-9.0.0.1.1.99.dev5.dist-info/WHEEL
odoo9_addon_project_closing-9.0.0.1.1.99.dev5.dist-info/namespace_packages.txt
odoo9_addon_project_closing-9.0.0.1.1.99.dev5.dist-info/top_level.txt
odoo_addons/project_closing/README.rst
odoo_addons/project_closing/__init__.py
odoo_addons/project_closing/__openerp__.py
odoo_addons/project_closing/i18n/de.po
odoo_addons/project_closing/i18n/es.po
odoo_addons/project_closing/i18n/es_MX.po
odoo_addons/project_closing/i18n/fi.po
odoo_addons/project_closing/i18n/fr.po
odoo_addons/project_closing/i18n/hr.po
odoo_addons/project_closing/i18n/it.po
odoo_addons/project_closing/i18n/nb.po
odoo_addons/project_closing/i18n/nl.po
odoo_addons/project_closing/i18n/project_closing.pot
odoo_addons/project_closing/i18n/pt.po
odoo_addons/project_closing/i18n/pt_BR.po
odoo_addons/project_closing/i18n/pt_PT.po
odoo_addons/project_closing/i18n/ro.po
odoo_addons/project_closing/i18n/sl.po
odoo_addons/project_closing/i18n/vi_VN.po
odoo_addons/project_closing/i18n/zh_CN.po
odoo_addons/project_closing/models/__init__.py
odoo_addons/project_closing/models/project.py
odoo_addons/project_closing/static/description/icon.png
