Metadata-Version: 2.1
Name: odoo9-addon-project-closing
Version: 9.0.0.1.1.99.dev5
Summary: Automatic account analytic closing when related project is closed, and if a project is opened, the related analytic account will be re-opened.
Home-page: http://www.camptocamp.com
Author: Camptocamp,Odoo Community Association (OCA)
Author-email: support@odoo-community.org
License: AGPL-3
Platform: UNKNOWN
Classifier: Programming Language :: Python
Classifier: Framework :: Odoo
Classifier: License :: OSI Approved :: GNU Affero General Public License v3
Requires-Python: ~=2.7
Requires-Dist: odoo (<9.1a,>=9.0a)
